doxycast/__init__.py
doxycast/builder.py
doxycast/config.py
doxycast/execute.py
doxycast/node.py
doxycast/parser.py
doxycast/utils.py
doxycast/writers/__init__.py
doxycast/writers/default.py
doxycast-2.0.0.dist-info/LICENSE
doxycast-2.0.0.dist-info/LICENSE.gpl
doxycast-2.0.0.dist-info/METADATA
doxycast-2.0.0.dist-info/WHEEL
doxycast-2.0.0.dist-info/top_level.txt
doxycast-2.0.0.dist-info/RECORD
