Metadata-Version: 2.1
Name: doxycast
Version: 2.0.0
Summary: Generate reStructuredText documentations from your C++ sources
Home-page: https://gitlab.com/pypp/doxycast
Author: Akib Azmain
Author-email: akib8492@gmail.com
License: GNU Lesser General Public License v3 or later (LGPLv3+)
Platform: UNKNOWN
Classifier: License :: OSI Approved :: GNU Lesser General Public License v3 or later (LGPLv3+)
Classifier: Framework :: Sphinx
Classifier: Framework :: Sphinx :: Extension
Classifier: Intended Audience :: Developers
Classifier: Development Status :: 4 - Beta
Classifier: Operating System :: Unix
Classifier: Programming Language :: Python :: 3
Classifier: Programming Language :: Python :: 3.8
Classifier: Programming Language :: Python :: Implementation :: CPython
Classifier: Topic :: Documentation
Classifier: Topic :: Documentation :: Sphinx
Classifier: Topic :: Software Development :: Documentation
Requires-Dist: sphinx
Provides-Extra: default_writer
Requires-Dist: breathe ; extra == 'default_writer'
